{
  "__type__": "cc.BitmapFont",
  "_name": "font-export",
  "_objFlags": 0,
  "_native": "",
  "fntDataStr": "",
  "spriteFrame": {
    "__uuid__": "047b7043-07dc-4008-978c-2515ab901325"
  },
  "fontSize": 48,
  "_fntConfig": {
    "commonHeight": 25,
    "fontSize": 48,
    "atlasName": "font-export.png",
    "fontDefDictionary": {
      "9": {
        "rect": {
          "x": 0,
          "y": 0,
          "width": 0,
          "height": 0
        },
        "xOffset": 0,
        "yOffset": 0,
        "xAdvance": 180
      },
      "32": {
        "rect": {
          "x": 0,
          "y": 0,
          "width": 0,
          "height": 0
        },
        "xOffset": 0,
        "yOffset": 0,
        "xAdvance": 6
      },
      "33": {
        "rect": {
          "x": 108,
          "y": 107,
          "width": 5,
          "height": 19
        },
        "xOffset": 0,
        "yOffset": 6,
        "xAdvance": 7
      },
      "34": {
        "rect": {
          "x": 35,
          "y": 120,
          "width": 10,
          "height": 6
        },
        "xOffset": 0,
        "yOffset": 6,
        "xAdvance": 12
      },
      "35": {
        "rect": {
          "x": 19,
          "y": 69,
          "width": 16,
          "height": 19
        },
        "xOffset": 0,
        "yOffset": 6,
        "xAdvance": 18
      },
      "36": {
        "rect": {
          "x": 84,
          "y": 65,
          "width": 12,
          "height": 25
        },
        "xOffset": 0,
        "yOffset": 3,
        "xAdvance": 14
      },
      "37": {
        "rect": {
          "x": 0,
          "y": 48,
          "width": 19,
          "height": 19
        },
        "xOffset": 0,
        "yOffset": 6,
        "xAdvance": 21
      },
      "38": {
        "rect": {
          "x": 0,
          "y": 69,
          "width": 17,
          "height": 20
        },
        "xOffset": 0,
        "yOffset": 6,
        "xAdvance": 19
      },
      "39": {
        "rect": {
          "x": 109,
          "y": 78,
          "width": 5,
          "height": 6
        },
        "xOffset": 0,
        "yOffset": 6,
        "xAdvance": 7
      },
      "40": {
        "rect": {
          "x": 108,
          "y": 0,
          "width": 7,
          "height": 24
        },
        "xOffset": 0,
        "yOffset": 6,
        "xAdvance": 9
      },
      "41": {
        "rect": {
          "x": 109,
          "y": 52,
          "width": 7,
          "height": 24
        },
        "xOffset": 0,
        "yOffset": 6,
        "xAdvance": 9
      },
      "42": {
        "rect": {
          "x": 76,
          "y": 112,
          "width": 11,
          "height": 10
        },
        "xOffset": 0,
        "yOffset": 6,
        "xAdvance": 13
      },
      "43": {
        "rect": {
          "x": 49,
          "y": 113,
          "width": 12,
          "height": 12
        },
        "xOffset": 0,
        "yOffset": 9,
        "xAdvance": 14
      },
      "44": {
        "rect": {
          "x": 99,
          "y": 52,
          "width": 6,
          "height": 7
        },
        "xOffset": 0,
        "yOffset": 21,
        "xAdvance": 8
      },
      "45": {
        "rect": {
          "x": 99,
          "y": 47,
          "width": 6,
          "height": 3
        },
        "xOffset": 0,
        "yOffset": 16,
        "xAdvance": 8
      },
      "46": {
        "rect": {
          "x": 109,
          "y": 86,
          "width": 5,
          "height": 4
        },
        "xOffset": 0,
        "yOffset": 21,
        "xAdvance": 7
      },
      "47": {
        "rect": {
          "x": 86,
          "y": 22,
          "width": 10,
          "height": 19
        },
        "xOffset": 0,
        "yOffset": 6,
        "xAdvance": 12
      },
      "48": {
        "rect": {
          "x": 53,
          "y": 91,
          "width": 14,
          "height": 20
        },
        "xOffset": 0,
        "yOffset": 6,
        "xAdvance": 16
      },
      "49": {
        "rect": {
          "x": 98,
          "y": 0,
          "width": 8,
          "height": 19
        },
        "xOffset": 0,
        "yOffset": 6,
        "xAdvance": 10
      },
      "50": {
        "rect": {
          "x": 70,
          "y": 44,
          "width": 13,
          "height": 19
        },
        "xOffset": 0,
        "yOffset": 6,
        "xAdvance": 15
      },
      "51": {
        "rect": {
          "x": 85,
          "y": 43,
          "width": 12,
          "height": 20
        },
        "xOffset": 0,
        "yOffset": 6,
        "xAdvance": 14
      },
      "52": {
        "rect": {
          "x": 54,
          "y": 48,
          "width": 14,
          "height": 19
        },
        "xOffset": 0,
        "yOffset": 6,
        "xAdvance": 16
      },
      "53": {
        "rect": {
          "x": 57,
          "y": 0,
          "width": 13,
          "height": 20
        },
        "xOffset": 0,
        "yOffset": 6,
        "xAdvance": 15
      },
      "54": {
        "rect": {
          "x": 39,
          "y": 26,
          "width": 14,
          "height": 20
        },
        "xOffset": 0,
        "yOffset": 6,
        "xAdvance": 16
      },
      "55": {
        "rect": {
          "x": 69,
          "y": 69,
          "width": 13,
          "height": 19
        },
        "xOffset": 0,
        "yOffset": 6,
        "xAdvance": 15
      },
      "56": {
        "rect": {
          "x": 53,
          "y": 69,
          "width": 14,
          "height": 20
        },
        "xOffset": 0,
        "yOffset": 6,
        "xAdvance": 16
      },
      "57": {
        "rect": {
          "x": 41,
          "y": 0,
          "width": 14,
          "height": 20
        },
        "xOffset": 0,
        "yOffset": 6,
        "xAdvance": 16
      },
      "58": {
        "rect": {
          "x": 115,
          "y": 92,
          "width": 4,
          "height": 14
        },
        "xOffset": 0,
        "yOffset": 11,
        "xAdvance": 6
      },
      "59": {
        "rect": {
          "x": 101,
          "y": 107,
          "width": 5,
          "height": 17
        },
        "xOffset": 0,
        "yOffset": 11,
        "xAdvance": 7
      },
      "60": {
        "rect": {
          "x": 84,
          "y": 92,
          "width": 11,
          "height": 13
        },
        "xOffset": 0,
        "yOffset": 9,
        "xAdvance": 13
      },
      "61": {
        "rect": {
          "x": 63,
          "y": 113,
          "width": 11,
          "height": 10
        },
        "xOffset": 0,
        "yOffset": 10,
        "xAdvance": 13
      },
      "62": {
        "rect": {
          "x": 97,
          "y": 92,
          "width": 10,
          "height": 13
        },
        "xOffset": 0,
        "yOffset": 9,
        "xAdvance": 12
      },
      "63": {
        "rect": {
          "x": 89,
          "y": 107,
          "width": 10,
          "height": 19
        },
        "xOffset": 0,
        "yOffset": 6,
        "xAdvance": 12
      },
      "64": {
        "rect": {
          "x": 0,
          "y": 26,
          "width": 19,
          "height": 20
        },
        "xOffset": 0,
        "yOffset": 8,
        "xAdvance": 21
      },
      "66": {
        "rect": {
          "x": 37,
          "y": 69,
          "width": 14,
          "height": 20
        },
        "xOffset": 0,
        "yOffset": 6,
        "xAdvance": 16
      },
      "68": {
        "rect": {
          "x": 55,
          "y": 22,
          "width": 14,
          "height": 20
        },
        "xOffset": 0,
        "yOffset": 6,
        "xAdvance": 16
      },
      "69": {
        "rect": {
          "x": 72,
          "y": 0,
          "width": 12,
          "height": 20
        },
        "xOffset": 0,
        "yOffset": 6,
        "xAdvance": 14
      },
      "71": {
        "rect": {
          "x": 69,
          "y": 90,
          "width": 13,
          "height": 20
        },
        "xOffset": 0,
        "yOffset": 6,
        "xAdvance": 15
      },
      "75": {
        "rect": {
          "x": 38,
          "y": 48,
          "width": 14,
          "height": 19
        },
        "xOffset": 0,
        "yOffset": 6,
        "xAdvance": 16
      },
      "77": {
        "rect": {
          "x": 0,
          "y": 101,
          "width": 17,
          "height": 19
        },
        "xOffset": 0,
        "yOffset": 6,
        "xAdvance": 19
      },
      "78": {
        "rect": {
          "x": 21,
          "y": 48,
          "width": 15,
          "height": 19
        },
        "xOffset": 0,
        "yOffset": 6,
        "xAdvance": 17
      },
      "80": {
        "rect": {
          "x": 71,
          "y": 22,
          "width": 13,
          "height": 19
        },
        "xOffset": 0,
        "yOffset": 6,
        "xAdvance": 15
      },
      "84": {
        "rect": {
          "x": 37,
          "y": 91,
          "width": 14,
          "height": 19
        },
        "xOffset": 0,
        "yOffset": 6,
        "xAdvance": 16
      },
      "86": {
        "rect": {
          "x": 21,
          "y": 26,
          "width": 16,
          "height": 20
        },
        "xOffset": 0,
        "yOffset": 6,
        "xAdvance": 18
      },
      "88": {
        "rect": {
          "x": 19,
          "y": 90,
          "width": 16,
          "height": 19
        },
        "xOffset": 0,
        "yOffset": 6,
        "xAdvance": 18
      },
      "91": {
        "rect": {
          "x": 99,
          "y": 21,
          "width": 7,
          "height": 24
        },
        "xOffset": 0,
        "yOffset": 6,
        "xAdvance": 9
      },
      "92": {
        "rect": {
          "x": 86,
          "y": 0,
          "width": 10,
          "height": 20
        },
        "xOffset": 0,
        "yOffset": 6,
        "xAdvance": 12
      },
      "93": {
        "rect": {
          "x": 108,
          "y": 26,
          "width": 7,
          "height": 24
        },
        "xOffset": 0,
        "yOffset": 6,
        "xAdvance": 9
      },
      "94": {
        "rect": {
          "x": 35,
          "y": 113,
          "width": 12,
          "height": 5
        },
        "xOffset": 0,
        "yOffset": 6,
        "xAdvance": 14
      },
      "95": {
        "rect": {
          "x": 0,
          "y": 122,
          "width": 15,
          "height": 2
        },
        "xOffset": 0,
        "yOffset": 26,
        "xAdvance": 17
      },
      "120": {
        "rect": {
          "x": 19,
          "y": 112,
          "width": 14,
          "height": 14
        },
        "xOffset": 0,
        "yOffset": 11,
        "xAdvance": 16
      },
      "123": {
        "rect": {
          "x": 98,
          "y": 65,
          "width": 9,
          "height": 24
        },
        "xOffset": 0,
        "yOffset": 6,
        "xAdvance": 11
      },
      "124": {
        "rect": {
          "x": 0,
          "y": 0,
          "width": 39,
          "height": 24
        },
        "xOffset": 0,
        "yOffset": 6,
        "xAdvance": 41
      },
      "125": {
        "rect": {
          "x": 0,
          "y": 91,
          "width": 17,
          "height": 8
        },
        "xOffset": 0,
        "yOffset": 14,
        "xAdvance": 19
      }
    },
    "kerningDict": {}
  },
  "_fontDefDictionary": null
}