{
  "__type__": "sp.SkeletonData",
  "_name": "Freespin",
  "_objFlags": 0,
  "_native": "",
  "_skeletonJson": {
    "skins": {
      "default": {
        "bonus101": {
          "bonus100": {
            "x": 1.59,
            "width": 196,
            "y": -1.24,
            "height": 221
          }
        },
        "eff2": {
          "eff": {
            "rotation": -1.15,
            "x": -1.9,
            "width": 410,
            "y": 1.19,
            "height": 410
          }
        },
        "bonus100": {
          "bonus100": {
            "x": 1.59,
            "width": 196,
            "y": -1.24,
            "height": 221
          }
        },
        "eff": {
          "eff": {
            "rotation": -1.15,
            "x": -1.9,
            "width": 410,
            "y": 1.19,
            "height": 410
          }
        },
        "text2": {
          "text": {
            "x": 0.68,
            "width": 236,
            "y": -5.64,
            "height": 70
          }
        },
        "text": {
          "text": {
            "x": 0.68,
            "width": 236,
            "y": -5.64,
            "height": 70
          }
        }
      }
    },
    "skeleton": {
      "images": "./images/",
      "width": 826.7,
      "spine": "3.7.94",
      "audio": "/Users/buisang/Storage/Job/zombie/zombie2/Anim/bonusFree/Freespin",
      "hash": "5mXsc6O0fUSS4xhPTAbsSJR4A6s",
      "height": 826.7
    },
    "slots": [
      {
        "attachment": "eff",
        "name": "eff",
        "bone": "bone2"
      },
      {
        "attachment": "eff",
        "blend": "additive",
        "name": "eff2",
        "bone": "bone7"
      },
      {
        "attachment": "bonus100",
        "name": "bonus100",
        "bone": "bone3"
      },
      {
        "attachment": "bonus100",
        "blend": "additive",
        "name": "bonus101",
        "bone": "bone6"
      },
      {
        "attachment": "text",
        "name": "text",
        "bone": "bone"
      },
      {
        "attachment": "text",
        "blend": "additive",
        "name": "text2",
        "bone": "bone5"
      }
    ],
    "bones": [
      {
        "name": "root"
      },
      {
        "scaleX": 1.7,
        "parent": "root",
        "scaleY": 1.7,
        "color": "00ff00ff",
        "name": "bone4",
        "x": -8.33,
        "y": 297.38
      },
      {
        "parent": "bone4",
        "name": "bone",
        "x": 8.65,
        "y": -80.74
      },
      {
        "parent": "bone4",
        "rotation": 1.15,
        "name": "bone2",
        "length": 58.42,
        "x": -5.75,
        "y": -11.53
      },
      {
        "parent": "bone4",
        "name": "bone3",
        "x": -0.26,
        "y": 23.36
      },
      {
        "parent": "bone4",
        "color": "ff0000ff",
        "name": "bone5",
        "x": 8.65,
        "y": -80.74
      },
      {
        "parent": "bone4",
        "color": "ff0000ff",
        "name": "bone6",
        "x": -0.26,
        "y": 23.36
      },
      {
        "parent": "bone4",
        "color": "ff0000ff",
        "rotation": -10.85,
        "name": "bone7",
        "length": 58.42,
        "x": -5.75,
        "y": -11.53
      }
    ],
    "animations": {
      "animation": {
        "slots": {
          "bonus101": {
            "color": [
              {
                "color": "ffffff00",
                "time": 0
              },
              {
                "color": "ffffff7e",
                "time": 0.5
              },
              {
                "color": "ffffff00",
                "time": 1
              }
            ]
          },
          "eff2": {
            "color": [
              {
                "color": "ffffff00",
                "time": 0
              },
              {
                "color": "ffffff84",
                "time": 0.5
              },
              {
                "color": "ffffff00",
                "time": 1
              }
            ]
          },
          "eff": {
            "color": [
              {
                "color": "ffffff89",
                "time": 0
              }
            ]
          },
          "text2": {
            "color": [
              {
                "color": "ffffff00",
                "time": 0
              },
              {
                "color": "ffffff80",
                "time": 0.5
              },
              {
                "color": "ffffff00",
                "time": 1
              }
            ]
          }
        },
        "bones": {
          "bone3": {
            "scale": [
              {
                "x": 0.8,
                "y": 0.8,
                "time": 0
              },
              {
                "x": 1,
                "y": 1,
                "time": 0.5
              },
              {
                "x": 0.8,
                "y": 0.8,
                "time": 1
              }
            ]
          },
          "bone5": {
            "scale": [
              {
                "x": 1,
                "y": 1,
                "time": 0
              },
              {
                "x": 1.2,
                "y": 1.2,
                "time": 1
              }
            ]
          },
          "bone7": {
            "scale": [
              {
                "x": 1,
                "y": 1,
                "time": 0
              },
              {
                "x": 1.3,
                "y": 1.3,
                "time": 1
              }
            ]
          },
          "bone6": {
            "scale": [
              {
                "x": 0.8,
                "y": 0.8,
                "time": 0
              },
              {
                "x": 1.1,
                "y": 1.1,
                "time": 1
              }
            ]
          }
        }
      }
    }
  },
  "_atlasText": "\nFreespin.png\nsize: 1024,512\nformat: RGBA8888\nfilter: Linear,Linear\nrepeat: none\nbonus100\n  rotate: false\n  xy: 414, 263\n  size: 196, 221\n  orig: 196, 221\n  offset: 0, 0\n  index: -1\neff\n  rotate: false\n  xy: 2, 74\n  size: 410, 410\n  orig: 410, 410\n  offset: 0, 0\n  index: -1\ntext\n  rotate: false\n  xy: 2, 2\n  size: 236, 70\n  orig: 236, 70\n  offset: 0, 0\n  index: -1\n",
  "textures": [
    {
      "__uuid__": "94f7d19f-2d88-418e-b788-b70381f7953e"
    }
  ],
  "textureNames": [
    "Freespin.png"
  ],
  "scale": 1
}